{
    "index": 20,
    "trackCount": 4,
    "enemies": [
        {
            "health": {
                "arrow": 10.0,
                "bullet": 0.0,
                "special": 0.0
            },
            "speed": 1.0,
            "track": 0,
            "timestamp": 4.0,
            "resourcePath": "EnemyPrefabs/Arrow Enemies/Butterfly/Butterfly Arrow"
        },
        {
            "health": {
                "arrow": 0.0,
                "bullet": 10.0,
                "special": 0.0
            },
            "speed": 1.0,
            "track": 0,
            "timestamp": 12.0,
            "resourcePath": "EnemyPrefabs/Bullet Enemies/Funky Bee/Funky Bee"
        },
        {
            "health": {
                "arrow": 10.0,
                "bullet": 0.0,
                "special": 0.0
            },
            "speed": 1.0,
            "track": 0,
            "timestamp": 24.0,
            "resourcePath": "EnemyPrefabs/Arrow Enemies/Butterfly/Butterfly Arrow"
        },
        {
            "health": {
                "arrow": 0.0,
                "bullet": 0.0,
                "special": 10.0
            },
            "speed": 0.9,
            "track": 0,
            "timestamp": 36.0,
            "resourcePath": "EnemyPrefabs/Special Enemies/Halloween Bee/Halloween Bee"
        },
        {
            "health": {
                "arrow": 0.0,
                "bullet": 5.0,
                "special": 8.0
            },
            "speed": 0.7,
            "track": 0,
            "timestamp": 52.0,
            "resourcePath": "EnemyPrefabs/Special Enemies/Steampunk Fly/Steampunk Fly"
        },
        {
            "health": {
                "arrow": 5.0,
                "bullet": 8.0,
                "special": 0.0
            },
            "speed": 0.7,
            "track": 0,
            "timestamp": 64.0,
            "resourcePath": "EnemyPrefabs/Bullet Enemies/Neo Fly/Neo Fly"
        },
        {
            "health": {
                "arrow": 0.0,
                "bullet": 7.0,
                "special": 6.0
            },
            "speed": 0.7,
            "track": 0,
            "timestamp": 80.0,
            "resourcePath": "EnemyPrefabs/Bullet Enemies/Magic Lady Bird/Magic Lady Bird"
        },
        {
            "health": {
                "arrow": 8.0,
                "bullet": 0.0,
                "special": 6.0
            },
            "speed": 0.9,
            "track": 0,
            "timestamp": 92.0,
            "resourcePath": "EnemyPrefabs/Arrow Enemies/Lady Bird/Lady Bird Arrow"
        },
        {
            "health": {
                "arrow": 0.0,
                "bullet": 0.0,
                "special": 10.0
            },
            "speed": 0.9,
            "track": 0,
            "timestamp": 104.0,
            "resourcePath": "EnemyPrefabs/Special Enemies/Halloween Bee/Halloween Bee"
        },
        {
            "health": {
                "arrow": 0.0,
                "bullet": 0.0,
                "special": 10.0
            },
            "speed": 0.9,
            "track": 1,
            "timestamp": 4.0,
            "resourcePath": "EnemyPrefabs/Special Enemies/Halloween Bee/Halloween Bee"
        },
        {
            "health": {
                "arrow": 6.0,
                "bullet": 0.0,
                "special": 7.0
            },
            "speed": 0.7,
            "track": 1,
            "timestamp": 16.0,
            "resourcePath": "EnemyPrefabs/Special Enemies/Bionic Lady Bird/Bionic Lady Bird"
        },
        {
            "health": {
                "arrow": 0.0,
                "bullet": 5.0,
                "special": 8.0
            },
            "speed": 0.7,
            "track": 1,
            "timestamp": 28.0,
            "resourcePath": "EnemyPrefabs/Special Enemies/Steampunk Fly/Steampunk Fly"
        },
        {
            "health": {
                "arrow": 6.0,
                "bullet": 0.0,
                "special": 7.0
            },
            "speed": 0.7,
            "track": 1,
            "timestamp": 40.0,
            "resourcePath": "EnemyPrefabs/Special Enemies/Bionic Lady Bird/Bionic Lady Bird"
        },
        {
            "health": {
                "arrow": 0.0,
                "bullet": 7.0,
                "special": 6.0
            },
            "speed": 0.7,
            "track": 1,
            "timestamp": 56.0,
            "resourcePath": "EnemyPrefabs/Bullet Enemies/Magic Lady Bird/Magic Lady Bird"
        },
        {
            "health": {
                "arrow": 0.0,
                "bullet": 10.0,
                "special": 0.0
            },
            "speed": 1.0,
            "track": 1,
            "timestamp": 68.0,
            "resourcePath": "EnemyPrefabs/Bullet Enemies/Funky Bee/Funky Bee"
        },
        {
            "health": {
                "arrow": 10.0,
                "bullet": 0.0,
                "special": 0.0
            },
            "speed": 1.0,
            "track": 1,
            "timestamp": 76.0,
            "resourcePath": "EnemyPrefabs/Arrow Enemies/Butterfly/Butterfly Arrow"
        },
        {
            "health": {
                "arrow": 0.0,
                "bullet": 0.0,
                "special": 10.0
            },
            "speed": 0.9,
            "track": 1,
            "timestamp": 88.0,
            "resourcePath": "EnemyPrefabs/Special Enemies/Halloween Bee/Halloween Bee"
        },
        {
            "health": {
                "arrow": 0.0,
                "bullet": 10.0,
                "special": 0.0
            },
            "speed": 1.0,
            "track": 1,
            "timestamp": 100.0,
            "resourcePath": "EnemyPrefabs/Bullet Enemies/Funky Bee/Funky Bee"
        },
        {
            "health": {
                "arrow": 5.0,
                "bullet": 8.0,
                "special": 0.0
            },
            "speed": 0.7,
            "track": 2,
            "timestamp": 4.0,
            "resourcePath": "EnemyPrefabs/Bullet Enemies/Neo Fly/Neo Fly"
        },
        {
            "health": {
                "arrow": 0.0,
                "bullet": 7.0,
                "special": 6.0
            },
            "speed": 0.7,
            "track": 2,
            "timestamp": 16.0,
            "resourcePath": "EnemyPrefabs/Bullet Enemies/Magic Lady Bird/Magic Lady Bird"
        },
        {
            "health": {
                "arrow": 8.0,
                "bullet": 0.0,
                "special": 6.0
            },
            "speed": 0.9,
            "track": 2,
            "timestamp": 28.0,
            "resourcePath": "EnemyPrefabs/Arrow Enemies/Lady Bird/Lady Bird Arrow"
        },
        {
            "health": {
                "arrow": 10.0,
                "bullet": 0.0,
                "special": 0.0
            },
            "speed": 1.0,
            "track": 2,
            "timestamp": 40.0,
            "resourcePath": "EnemyPrefabs/Arrow Enemies/Butterfly/Butterfly Arrow"
        },
        {
            "health": {
                "arrow": 5.0,
                "bullet": 8.0,
                "special": 0.0
            },
            "speed": 0.7,
            "track": 2,
            "timestamp": 52.0,
            "resourcePath": "EnemyPrefabs/Bullet Enemies/Neo Fly/Neo Fly"
        },
        {
            "health": {
                "arrow": 0.0,
                "bullet": 7.0,
                "special": 6.0
            },
            "speed": 0.7,
            "track": 2,
            "timestamp": 64.0,
            "resourcePath": "EnemyPrefabs/Bullet Enemies/Magic Lady Bird/Magic Lady Bird"
        },
        {
            "health": {
                "arrow": 5.0,
                "bullet": 8.0,
                "special": 0.0
            },
            "speed": 0.7,
            "track": 2,
            "timestamp": 80.0,
            "resourcePath": "EnemyPrefabs/Bullet Enemies/Neo Fly/Neo Fly"
        },
        {
            "health": {
                "arrow": 0.0,
                "bullet": 5.0,
                "special": 8.0
            },
            "speed": 0.7,
            "track": 2,
            "timestamp": 92.0,
            "resourcePath": "EnemyPrefabs/Special Enemies/Steampunk Fly/Steampunk Fly"
        },
        {
            "health": {
                "arrow": 5.0,
                "bullet": 8.0,
                "special": 0.0
            },
            "speed": 0.7,
            "track": 2,
            "timestamp": 104.0,
            "resourcePath": "EnemyPrefabs/Bullet Enemies/Neo Fly/Neo Fly"
        },
        {
            "health": {
                "arrow": 0.0,
                "bullet": 5.0,
                "special": 8.0
            },
            "speed": 0.7,
            "track": 3,
            "timestamp": 4.0,
            "resourcePath": "EnemyPrefabs/Special Enemies/Steampunk Fly/Steampunk Fly"
        },
        {
            "health": {
                "arrow": 0.0,
                "bullet": 7.0,
                "special": 6.0
            },
            "speed": 0.7,
            "track": 3,
            "timestamp": 12.0,
            "resourcePath": "EnemyPrefabs/Bullet Enemies/Magic Lady Bird/Magic Lady Bird"
        },
        {
            "health": {
                "arrow": 5.0,
                "bullet": 8.0,
                "special": 0.0
            },
            "speed": 0.7,
            "track": 3,
            "timestamp": 24.0,
            "resourcePath": "EnemyPrefabs/Bullet Enemies/Neo Fly/Neo Fly"
        },
        {
            "health": {
                "arrow": 0.0,
                "bullet": 10.0,
                "special": 0.0
            },
            "speed": 1.0,
            "track": 3,
            "timestamp": 36.0,
            "resourcePath": "EnemyPrefabs/Bullet Enemies/Funky Bee/Funky Bee"
        },
        {
            "health": {
                "arrow": 8.0,
                "bullet": 0.0,
                "special": 6.0
            },
            "speed": 0.9,
            "track": 3,
            "timestamp": 48.0,
            "resourcePath": "EnemyPrefabs/Arrow Enemies/Lady Bird/Lady Bird Arrow"
        },
        {
            "health": {
                "arrow": 6.0,
                "bullet": 0.0,
                "special": 7.0
            },
            "speed": 0.7,
            "track": 3,
            "timestamp": 60.0,
            "resourcePath": "EnemyPrefabs/Special Enemies/Bionic Lady Bird/Bionic Lady Bird"
        },
        {
            "health": {
                "arrow": 0.0,
                "bullet": 5.0,
                "special": 8.0
            },
            "speed": 0.7,
            "track": 3,
            "timestamp": 72.0,
            "resourcePath": "EnemyPrefabs/Special Enemies/Steampunk Fly/Steampunk Fly"
        },
        {
            "health": {
                "arrow": 6.0,
                "bullet": 0.0,
                "special": 7.0
            },
            "speed": 0.7,
            "track": 3,
            "timestamp": 84.0,
            "resourcePath": "EnemyPrefabs/Special Enemies/Bionic Lady Bird/Bionic Lady Bird"
        },
        {
            "health": {
                "arrow": 0.0,
                "bullet": 7.0,
                "special": 6.0
            },
            "speed": 0.7,
            "track": 3,
            "timestamp": 96.0,
            "resourcePath": "EnemyPrefabs/Bullet Enemies/Magic Lady Bird/Magic Lady Bird"
        },
        {
            "health": {
                "arrow": 6.0,
                "bullet": 0.0,
                "special": 7.0
            },
            "speed": 0.7,
            "track": 3,
            "timestamp": 104.0,
            "resourcePath": "EnemyPrefabs/Special Enemies/Bionic Lady Bird/Bionic Lady Bird"
        }
    ]
}